{
    "code":200,
    "msg":"ok",
    "time":"2017-01-01",
    "data":{
        "history_line":[
            {
                "deal_time":"2018-07-12",
                "x":1.07,
                "y":37.21
            },
            {
                "deal_time":"2018-07-13",
                "x":1.9,
                "y":36.21
            }, 
            {
                "deal_time":"2018-07-14",
                "x":4,
                "y":35.21
            },
            {
                "deal_time":"2018-07-15",
                "x":7.8,
                "y":30.21
            },    
            {
                "deal_time":"2018-07-17",
                "x":12.2,
                "y":37.21
            },    
            {
                "deal_time":"2018-07-18",
                "x":9.07,
                "y":27.21
            },    
            {
                "deal_time":"2018-07-19",
                "x":5.07,
                "y":17.21
            },    
            {
                "deal_time":"2018-07-20",
                "x":21.07,
                "y":22
            },    
            {
                "deal_time":"2018-07-21",
                "x":19.07,
                "y":25.21
            },    
            {
                "deal_time":"2018-07-22",
                "x":15.07,
                "y":20.21
            },    
            {
                "deal_time":"2018-07-23",
                "x":8.07,
                "y":33.21
            },    
            {
                "deal_time":"2018-07-24",
                "x":12.07,
                "y":47.21
            },    
            {
                "deal_time":"2018-07-25",
                "x":10.07,
                "y":10.21
            }
        ],
        "month_facet":1,
        "risk_level":6
    }
}